<?xml version='1.0' encoding='UTF-8'?>
<!-- Thes regex rules have been tested against what I had at hand, some patterns against 5000+ URLs, others agains a few hundreds. -->
<!-- Author: Christopher Isene<christopher.isene@gmail.com> -->
<rulesets>
  <ruleset name="Anchor.fm">
    <matching>^http(s)?\x3a\x2f\x2fanchor\x2efm\x2fs\x2f([0-9a-f]{1,})\x2fpodcast\x2frss$</matching>
  </ruleset>
  <ruleset name="Spreaker">
    <matching>^http(s)?\x3a\x2f\x2fwww\x2espreaker\x2ecom\x2fshow\x2f(\d{1,})\x2fepisodes\x2ffeed$</matching>
    <matching>^http(s)?\x3a\x2f\x2fwww\x2espreaker\x2ecom\x2fuser\x2f(\d{1,})\x2fepisodes\x2ffeed$</matching>
    <matching>^http(s)?\x3a\x2f\x2fwww\x2espreaker\x2ecom\x2fihr\x2fshow\x2f(\d{1,})\x2fepisodes\x2ffeed\x2dpassthrough$</matching>
  </ruleset>
  <ruleset name="Ivoox">
    <matching>^http(s)?\x3a\x2f\x2f([a-z]{1,})\x2eivoox\x2ecom\x2f(([a-z]{1,})\x2f)?([a-z0-9\x2d\x5f]{1,})\x5ff\d{1,}\x5ffiltro\x5f1\x2exml$</matching>
  </ruleset>
  <ruleset name="SoundCloud">
    <matching>^http(s)?\x3a\x2f\x2ffeeds\x2esoundcloud\x2ecom\x2fusers\x2fsoundcloud\x3ausers\x3a(\d{1,})\x2fsounds\x2erss$</matching>
  </ruleset>
  <ruleset name="LibSyn">
    <matching>^http(s)?\x3a\x2f\x2f([a-z0-9\x2d]{1,})\x2elibsyn\x2ecom\x2frss$</matching>
  </ruleset>
  <ruleset name="PodBean">
    <matching>^http(s)?\x3a\x2f\x2f([a-z0-9\x2d]{1,})\x2epodbean\x2ecom\x2ffeed\x2exml$</matching>
    <matching>^http(s)?\x3a\x2f\x2f([a-z0-9\x2d]{1,})\x2epodbean\x2ecom\x2ffeed\x2f$</matching>
  </ruleset>
  <ruleset name="BuzzSprout.com">
    <matching>^http(s)?\x3a\x2f\x2ffeeds\x2ebuzzsprout\x2ecom\x2f(\d{1,})\x2erss$</matching>
  </ruleset>
  <ruleset name="LibriVox.org">
    <matching>^http(s)?\x3a\x2f\x2flibrivox\x2eorg\x2frss\x2f(\d{1,})$</matching>
  </ruleset>
  <ruleset name="FeedBurner.com">
    <matching>^http(s)?\x3a\x2f\x2ffeeds\x2efeedburner\x2ecom\x2f([a-z0-9\x2f\x2d\x5f]{1,})$</matching>
  </ruleset>
  <ruleset name="PromoDJ.com">
    <matching>^http(s)?\x3a\x2f\x2fpromodj\x2ecom\x2f([a-z0-9\x2d\x2e]{1,})\x2f([a-z0-9\x2d\x2e]{1,})\x2exml$</matching>
  </ruleset>
  <ruleset name="LoyalBooks.com">
    <matching>^http(s)?\x3a\x2f\x2fwww\x2eloyalbooks\x2ecom\x2fbook\x2f([a-z0-9\x25\x2d\x5f]{1,})\x2ffeed$</matching>
  </ruleset>
  <ruleset name="AudioBoom.com">
    <matching>^http(s)?\x3a\x2f\x2faudioboom\x2ecom\x2fchannels\x2f(\d{1,})\x2erss$</matching>
    <matching>^http(s)?\x3a\x2f\x2faudioboom\x2ecom\x2fchannel\x2f([a-z0-9\x2e\x2d\x5f]{1,})\x2erss$</matching>
    <matching>^http(s)?\x3a\x2f\x2faudioboom\x2ecom\x2fplaylists\x2f([a-z0-9\x2e\x2d]{1,})\x2erss$</matching>
  </ruleset>
  <ruleset name="SimpleCast.com">
    <matching>^http(s)?\x3a\x2f\x2ffeeds\x2esimplecast\x2ecom\x2f([a-z0-9\x5f]{1,})$</matching>
    <matching>^http(s)?\x3a\x2f\x2f(rss\x2e)?simplecast\x2ecom\x2fpodcasts\x2f(\d{1,})\x2frss$</matching>
  </ruleset>
  <ruleset name="PodOmatic.com">
    <matching>^http(s)?\x3a\x2f\x2f([a-z0-9\x2d\x5f]{1,})\x2epodomatic\x2ecom\x2f(rss2|archive)\x2exml$</matching>
  </ruleset>
  <ruleset name="ACast.com">
    <matching>^http(s)?\x3a\x2f\x2faccess\x2eacast\x2ecom\x2frss\x2f([a-z0-9]{1,})\x2fdefault$</matching>
    <matching>^http(s)?\x3a\x2f\x2ffeeds\x2eacast\x2ecom\x2fpublic\x2fshows\x2f([a-z0-9\x2d\x5f]{1,})$</matching>
    <matching>^http(s)?\x3a\x2f\x2frss\x2eacast\x2ecom\x2f([a-z0-9\x2d\x5f]{1,})$</matching>
  </ruleset>
  <ruleset name="OmnyContent.com">
    <matching>^http(s)?\x3a\x2f\x2fwww\x2eomnycontent\x2ecom\x2fd\x2fplaylist\x2f([a-f0-9\x2d]{36})\x2f([a-f0-9\x2d]{36})\x2f([a-f0-9\x2d]{36})\x2fpodcast\x2erss$</matching>
  </ruleset>
  <ruleset name="Hakawati.fm">
    <matching>^http(s)?\x3a\x2f\x2fhakawati\x2efm\x2fchannels\x2frss\x2f(\d{1,})$</matching>
  </ruleset>
  <ruleset name="Whooshkaa.com">
    <matching>^http(s)?\x3a\x2f\x2frss\x2ewhooshkaa\x2ecom\x2frss\x2fpodcast\x2fid\x2f(\d{1,})(\x2f)?$</matching>
  </ruleset>
  <ruleset name="MegaPhone.fm">
    <matching>^http(s)?\x3a\x2f\x2ffeeds\x2emegaphone\x2efm\x2f([a-z0-9\x2d]{1,})(\x2f)?$</matching>
    <removes>
      <remove>\x3flimit\x3d\d{1,}</remove>
      <remove>\x3fselected\x3d([a-z0-9]{1,})</remove>
      <remove>\x3fcb\x3d(\d{1,})</remove>
      <remove>\x3fn\x3d([a-z0-9]{1,})</remove>
      <remove>\x3fformat\x3drss</remove>
    </removes>
  </ruleset>
  <ruleset name="RadioFrance-Podcast.net">
    <matching>^http(s)?\x3a\x2f\x2fradiofrance\x2dpodcast\x2enet\x2fpodcast(\d{1,})\x2frss\x5f(\d{1,})\x2exml$</matching>
    <removes>
      <remove>\x3fformat\x3dxml</remove>
    </removes>
  </ruleset>
  <ruleset name="Podigee.io">
    <matching>^http(s)?\x3a\x2f\x2f([a-z0-9\x2d\x2e]{1,})\x2epodigee\x2eio\x2ffeed\x2f([a-z0-9]{1,})$</matching>
  </ruleset>
  <ruleset name="SquareSpace.com">
    <matching>^http(s)?\x3a\x2f\x2f([a-z0-9\x2d]{1,})\x2esquarespace\x2ecom\x2f([a-z0-9\x2d\x2f]{1,})?\x3fformat\x3drss$</matching>
    <removes>
      <remove>\x3fcategory\x3d([a-z0-9\x25]{1,})</remove>
    </removes>
  </ruleset>
  <ruleset name="RDL.de">
    <matching>^http(s)?\x3a\x2f\x2frdl\x2ede\x2fpodcast\x2f(\d{1,})\x2fall$</matching>
  </ruleset>
  <ruleset name="Transistor.fm">
    <matching>^http(s)?\x3a\x2f\x2ffeeds\x2etransistor\x2efm\x2f([a-z0-9\x2d]{1,})$</matching>
  </ruleset>

  <ruleset name="SermonAudio.com">
    <matching>^http(s)?\x3a\x2f\x2f(www|rss)\x2esermonaudio\x2ecom\x2frss\x5f(source|search|special)\x2e(asp|rss)\x3f(sourceid|type|filter|seriesonly|speakeronly|keyword|langonly|eventonly)\x3d</matching>
  </ruleset>

  <ruleset name="Art19.com">
    <matching>^http(s)?\x3a\x2f\x2frss\x2eart19\x2ecom\x2f([a-z0-9\x2d\x2f\x5f]{1,})$</matching>
  </ruleset>

  <ruleset name="Blubrry.com">
    <matching>^http(s)?\x3a\x2f\x2f([a-z0-9\x2d\x5f]{1,})\x2eblubrry\x2ecom\x2ffeed\x2fpodcast(\x2f)?$</matching>
    <matching>^http(s)?\x3a\x2f\x2fmedia\x2eblubrry\x2ecom\x2f([a-z0-9\x2d\x2e\x2f\x5f]{1,})(\x3fformat\x3drss)?$</matching>
    <matching>^http(s)?\x3a\x2f\x2ffeeds\x2eblubrry\x2ecom\x2ffeeds\x2f([a-z0-9\x2d\x5f]{1,})\x2exml$</matching>
  </ruleset>

  <ruleset name="Podcaster.de">
    <matching>^http(s)?\x3a\x2f\x2f([a-z0-9\x2d]{1,})\x2epodcaster\x2ede\x2f([a-z0-9\x2d\x5f]{1,})\x2erss$</matching>
  </ruleset>

  <ruleset name="SubSplash.com">
    <matching>^http(s)?\x3a\x2f\x2fpodcasts\x2esubsplash\x2ecom\x2f([a-z0-9]{1,})\x2fpodcast\x2erss$</matching>
  </ruleset>

  <ruleset name="Iono.fm">
    <matching>^http(s)?\x3a\x2f\x2fiono\x2efm\x2frss\x2fchan\x2f(\d{1,})$</matching>
    <matching>^http(s)?\x3a\x2f\x2fiono\x2efm\x2frss\x2ffeed\x2f([a-z0-9]{1,})$</matching>
    <matching>^http(s)?\x3a\x2f\x2fiono\x2efm\x2frss\x2fprov\x2f([0-9]{1,})$</matching>
  </ruleset>

  <ruleset name="Lizhi.fm">
    <matching>^http(s)?\x3a\x2f\x2frss\x2elizhi\x2efm\x2frss\x2f(\d{1,})\x2exml$</matching>
  </ruleset>

  <ruleset name="BlogtalkRadio.com">
    <matching>^http(s)?\x3a\x2f\x2fwww\x2eblogtalkradio\x2ecom\x2f([a-z0-9\x2d\x5f]{1,})\x2fpodcast$</matching>
  </ruleset>

  <ruleset name="FireSide.fm">
    <matching>^http(s)?\x3a\x2f\x2f([a-z0-9\x2d]{1,})\x2efireside\x2efm\x2frss$</matching>
    <matching>^http(s)?\x3a\x2f\x2ffeeds\x2efireside\x2efm\x2f([a-z0-9\x2d]{1,})\x2frss$</matching>
  </ruleset>

  <ruleset name="Sermon.net">
    <matching>^http(s)?\x3a\x2f\x2f([a-z0-9\x2d]{1,})\x2esermon\x2enet\x2frss(\x2f)?([a-z0-9\x2d\x2f\x5f]{1,})?$</matching>
  </ruleset>

  <ruleset name="NPR.org">
    <matching>^http(s)?\x3a\x2f\x2ffeeds\x2enpr\x2eorg\x2f(\d{1,})\x2fpodcast\x2exml$</matching>
    <matching>^http(s)?\x3a\x2f\x2fwww\x2enpr\x2eorg\x2frss\x2fpodcast\x2ephp\x3fid\x3d(\d{1,})$</matching>
    <matching>^http(s)?\x3a\x2f\x2fwww\x2enpr\x2eorg\x2frss\x2fpodlayer\x2ephp\x3fid\x3d(\d{1,})$</matching>


    <removes>
      <remove>\x26uid\x3d([a-z0-9]{1,})</remove>
      <remove>\x3f\x5frp\x5ftoken\x3d([a-z0-9]{1,})</remove>
    </removes>
  </ruleset>

  <ruleset name="Echo.Msk.Ru">
    <matching>^http(s)?\x3a\x2f\x2fecho\x2emsk\x2eru\x2fcontributors\x2f(\d{1,})\x2frss\x2daudio\x2exml$</matching>
    <matching>^http(s)?\x3a\x2f\x2fecho\x2emsk\x2eru\x2fcontributors\x2f([a-z\x2d]{1,})\x2frss\x2daudio\x2exml$</matching>
    <matching>^http(s)?\x3a\x2f\x2fecho\x2emsk\x2eru\x2fguests\x2f(\d{1,})\x2frss\x2daudio\x2exml$</matching>
    <matching>^http(s)?\x3a\x2f\x2fecho\x2emsk\x2eru\x2fguests\x2f(\d{1,})\x2decho\x2frss\x2daudio\x2exml$</matching>
    <matching>^http(s)?\x3a\x2f\x2fecho\x2emsk\x2eru\x2fprograms\x2f([a-z0-9\x2d\x5f]{1,})\x2frss\x2daudio\x2exml$</matching>

  </ruleset>

  <ruleset name="Podster.fm">
    <matching>^http(s)?\x3a\x2f\x2fpodster\x2efm\x2frss\x2exml\x3fpid\x3d(\d{1,})$</matching>
  </ruleset>

  <ruleset name="PodcastOne.com">
    <matching>^http(s)?\x3a\x2f\x2forigin\x2epodcastone\x2ecom\x2fpodcast\x3fcategoryID2\x3d(\d{1,})$</matching>
  </ruleset>

  <ruleset name="Captivate.fm">
    <matching>^http(s)?\x3a\x2f\x2ffeeds\x2ecaptivate\x2efm\x2f([a-z0-9\x2d\x5f]{1,})\x2f$</matching>
  </ruleset>

  <ruleset name="Messy.fm">
    <matching>^http(s)?\x3a\x2f\x2fwww\x2emessy\x2efm\x2fapi\x2fshow\x2f(\d{1,})\x2frss$</matching>
  </ruleset>

  <ruleset name="RTVE.es">
    <matching>^http(s)?\x3a\x2f\x2fapi\x2ertve\x2ees\x2fapi\x2fprogramas\x2f(\d{1,})\x2f(audios|multimedias)\x2erss$</matching>
  </ruleset>

  <ruleset name="ShoutEngine.com">
    <matching>^http(s)?\x3a\x2f\x2fshoutengine\x2ecom\x2f([a-z0-9\x2d\x5f]{1,})\x2exml$</matching>
  </ruleset>

  <ruleset name="CastBox.fm">
    <matching>^http(s)?\x3a\x2f\x2frss\x2ecastbox\x2efm\x2feverest\x2f([a-f0-9]{32})\x2exml$</matching>
  </ruleset>

  <ruleset name="FeedPreess.me">
    <matching>^http(s)?\x3a\x2f\x2ffeedpress\x2eme\x2f([a-z0-9\x2d\x5f]{1,})$</matching>
  </ruleset>

  <ruleset name="LibsynPro.com">
    <matching>^http(s)?\x3a\x2f\x2f([a-z0-9\x2d\x2e]{1,})\x2elibsynpro\x2ecom\x2f([a-z0-9\x2d\x2e\x2f\x5f]{1,})$</matching>
  </ruleset>

  <ruleset name="BBCi.co.uk">
    <matching>^http(s)?\x3a\x2f\x2fpodcasts\x2efiles\x2ebbci\x2eco\x2euk\x2f([a-z0-9]{8})\x2erss$</matching>
  </ruleset>

  <ruleset name="Podcasts.com">
    <matching>^http(s)?\x3a\x2f\x2fwww\x2epodcasts\x2ecom\x2frss\x5ffeed\x2f([a-f0-9]{32})$</matching>
  </ruleset>

  <ruleset name="PodcastMirror.com">
    <matching>^http(s)?\x3a\x2f\x2ffeeds\x2epodcastmirror\x2ecom\x2f([a-z0-9\x2d\x5f]{1,})$</matching>
  </ruleset>

  <ruleset name="NDR.de">
    <matching>^http(s)?\x3a\x2f\x2fwww\x2endr\x2ede\x2f([a-z0-9\x2d\x2f\x5f]{1,})\x2fpodcast(\d{1,})\x2exml$</matching>
    <matching>^http(s)?\x3a\x2f\x2fwww\x2endr\x2ede\x2fpodcast\x2f([a-z0-9]{1,})\x2exml$</matching>
    <matching>^http(s)?\x3a\x2f\x2fwww\x2endr\x2ede\x2fpodcastlink\x2f([a-z0-9\x2d\x5f]{1,})\x2exml$</matching>
    <matching>^http(s)?\x3a\x2f\x2fwww1\x2endr\x2ede\x2fpodcast\x2fpodcast(\d{1,})\x2exml$</matching>
    <matching>^http(s)?\x3a\x2f\x2f([a-z0-9]{1,})\x2endr\x2ede\x2f([a-z0-9]{1,})\x2fpodcast\x2f([a-z0-9]{1,})\x2exml$</matching>
  </ruleset>

  <ruleset name="Blubrry.net">
    <matching>^http(s)?\x3a\x2f\x2f([a-z0-9\x2d]{1,})\x2eblubrry\x2enet\x2ffeed\x2f([a-z0-9\x2d\x2f\x5f]{1,})$</matching>
    <matching>^http(s)?\x3a\x2f\x2f([a-z0-9\x2d]{1,})\x2eblubrry\x2enet\x2fcategory\x2f([a-z0-9\x2d\x5f]{1,})\x2ffeed([a-z0-9\x2d\x2f]{1,})$</matching>
    <matching>^http(s)?\x3a\x2f\x2f([a-z0-9\x2d]{1,})\x2eblubrry\x2enet\x2f\x3ffeed\x3d([a-z]{1,})$</matching>
    <matching>^http(s)?\x3a\x2f\x2f([a-z0-9\x2d]{1,})\x2eblubrry\x2enet\x2ffeed\x2f$</matching>
  </ruleset>

  <ruleset name="RFI.fr">
    <matching>^http(s)?\x3a\x2f\x2fbr\x2erfi\x2efr\x2fprogramas\x2f([a-z0-9\x2d]{1,})\x2fpodcast(\x2f)?$</matching>
    <matching>^http(s)?\x3a\x2f\x2fcn\x2erfi\x2efr\x2f([a-f0-9\x25]{1,})\x2f([a-f0-9\x25]{1,})\x2fpodcast(\x2f)?$</matching>
    <matching>^http(s)?\x3a\x2f\x2fen\x2erfi\x2efr\x2f([a-z0-9\x2d\x5f]{1,})\x2f([a-z0-9\x2d\x2f]{1,})\x2fpodcast(\x2f)?$</matching>
    <matching>^http(s)?\x3a\x2f\x2fes\x2erfi\x2efr\x2f([a-z0-9\x2d\x5f]{1,})\x2f([a-z0-9\x2d\x2f]{1,})\x2fpodcast(\x2f)?$</matching>
    <matching>^http(s)?\x3a\x2f\x2fha\x2erfi\x2efr\x2f([a-z0-9\x2d\x5f]{1,})\x2f([a-z0-9\x2d\x2f]{1,})\x2fpodcast(\x2f)?$</matching>
    <matching>^http(s)?\x3a\x2f\x2fkm\x2erfi\x2efr\x2f([a-z0-9\x2d\x5f]{1,})\x2f([a-z0-9\x2d\x2f]{1,})\x2fpodcast(\x2f)?$</matching>
    <matching>^http(s)?\x3a\x2f\x2fpt\x2erfi\x2efr\x2f([a-z0-9\x2d\x5f]{1,})\x2f([a-z0-9\x2d\x2f]{1,})\x2fpodcast(\x2f)?$</matching>
    <matching>^http(s)?\x3a\x2f\x2fsw\x2erfi\x2efr\x2f([a-z0-9\x2d\x5f]{1,})\x2f([a-z0-9\x2d\x2f]{1,})\x2fpodcast(\x2f)?$</matching>
    <matching>^http(s)?\x3a\x2f\x2fvi\x2erfi\x2efr\x2f([a-z0-9\x2d\x5f]{1,})\x2f([a-z0-9\x2d\x2f]{1,})\x2fpodcast(\x2f)?$</matching>
    <matching>^http(s)?\x3a\x2f\x2fwww\x2erfi\x2efr\x2fbr\x2f(emission|podcasts)\x2f([a-z0-9\x25\x2d\x2f]{1,})\x2fpodcast$</matching>
    <matching>^http(s)?\x3a\x2f\x2fwww\x2erfi\x2efr\x2fcn\x2f([a-z0-9\x25\x2d\x2f]{1,})\x2fpodcast$</matching>
    <matching>^http(s)?\x3a\x2f\x2fwww\x2erfi\x2efr\x2femission\x2f([a-z0-9\x25\x2d\x2f]{1,})\x2fpodcast$</matching>
    <matching>^http(s)?\x3a\x2f\x2fwww\x2erfi\x2efr\x2fen\x2f([a-z0-9\x25\x2d\x2f]{1,})\x2fpodcast$</matching>
    <matching>^http(s)?\x3a\x2f\x2fwww\x2erfi\x2efr\x2fes\x2f([a-z0-9\x25\x2d\x2f]{1,})\x2fpodcast$</matching>
    <matching>^http(s)?\x3a\x2f\x2fwww\x2erfi\x2efr\x2ffr\x2f([a-z0-9\x25\x2d\x2f]{1,})\x2fpodcast$</matching>
    <matching>^http(s)?\x3a\x2f\x2fwww\x2erfi\x2efr\x2fha\x2f([a-z0-9\x25\x2d\x2f]{1,})\x2fpodcast$</matching>
    <matching>^http(s)?\x3a\x2f\x2fwww\x2erfi\x2efr\x2fkm\x2f([a-z0-9\x25\x2d\x2f]{1,})\x2fpodcast$</matching>
    <matching>^http(s)?\x3a\x2f\x2fwww\x2erfi\x2efr\x2fpt\x2f([a-z0-9\x25\x2d\x2f]{1,})\x2fpodcast$</matching>
    <matching>^http(s)?\x3a\x2f\x2fwww\x2erfi\x2efr\x2fru\x2f([a-z0-9\x25\x2d\x2f]{1,})\x2fpodcast$</matching>
    <matching>^http(s)?\x3a\x2f\x2fwww\x2erfi\x2efr\x2fsw\x2f([a-z0-9\x25\x2d\x2f]{1,})\x2fpodcast$</matching>
    <matching>^http(s)?\x3a\x2f\x2fwww\x2erfi\x2efr\x2fvi\x2f([a-z0-9\x25\x2d\x2f]{1,})\x2fpodcast$</matching>
    <matching>^http(s)?\x3a\x2f\x2fwww1\x2erfi\x2efr\x2fradiofr\x2fpodcast\x2f([a-z0-9\x2d\x5f]{1,})\x2exml$</matching>

  </ruleset>

  <ruleset name="Hearthis.at">
    <matching>^http(s)?\x3a\x2f\x2fhearthis\x2eat\x2f([a-z0-9\x2d\x2e\x5f]{1,})\x2fpodcast\x2f$</matching>
    <matching>^http(s)?\x3a\x2f\x2fhearthis\x2eat\x2fset\x2f([a-z0-9\x2d]{1,})\x2fpodcast\x2f(rss\x2f)?$</matching>
  </ruleset>

  <ruleset name="Seesaa.net">
    <matching>^http(s)?\x3a\x2f\x2f([a-z0-9\x2d]{1,})\x2eseesaa\x2enet\x2f([a-z0-9\x2d\x5f]{1,})\x2erdf$</matching>
  </ruleset>

  <ruleset name="Ausha.co">
    <matching>^http(s)?\x3a\x2f\x2ffeed\x2eausha\x2eco\x2f([a-z0-9]{12})$</matching>
  </ruleset>

  <ruleset name="PodCache.net">
    <matching>^http(s)?\x3a\x2f\x2fapi\x2epodcache\x2enet\x2fshows\x2f([a-f0-9\x2d]{36})\x2ffeed$</matching>
    <matching>^http(s)?\x3a\x2f\x2fstaging\x2dapi\x2epodcache\x2enet\x2fshows\x2f([a-f0-9\x2d]{36})\x2ffeed$</matching>
  </ruleset>

  <ruleset name="Prisasd.com">
    <matching>^http(s)?\x3a\x2f\x2ffapi\x2dtop\x2eprisasd\x2ecom\x2fpodcast\x2f([a-z0-9\x2d\x2f\x5f]{1,})\x2f([a-z0-9\x2d\x5f]{1,})(\x2exml)?$</matching>
  </ruleset>

  <ruleset name="PodPoint.com">
    <matching>^http(s)?\x3a\x2f\x2fpodpoint\x2ecom\x2ffeed\x2f(\d{1,})$</matching>
  </ruleset>

  <ruleset name="WordPress.com">
    <matching>^http(s)?\x3a\x2f\x2f([a-z0-9\x2d]{1,})\x2ewordpress\x2ecom\x2f([a-z0-9\x25\x2d\x2f\x5f]{1,})?feed\x2f$</matching>
  </ruleset>


</rulesets>